filewriter/__init__.py
filewriter-2.0.2.dist-info/LICENSE
filewriter-2.0.2.dist-info/METADATA
filewriter-2.0.2.dist-info/WHEEL
filewriter-2.0.2.dist-info/top_level.txt
filewriter-2.0.2.dist-info/RECORD
