Metadata-Version: 2.1
Name: filewriter
Version: 2.0.2
Summary: json supported easy debugger for python, in files. can also read.
Home-page: https://github.com/ebsaral/filewriter
Author: Emin Bugra Saral
Author-email: eminbugrasaral@me.com
License: BSD
Project-URL: Documentation, https://github.com/ebsaral/filewriter
Project-URL: Funding, https://github.com/ebsaral/filewriter
Project-URL: Source, https://github.com/ebsaral/filewriter
Keywords: json supported easy debugger for python debug file writer reader
Platform: UNKNOWN
Classifier: License :: OSI Approved :: BSD License
Classifier: Operating System :: OS Independent
Classifier: Programming Language :: Python
Classifier: Programming Language :: Python :: 3
Classifier: Topic :: Text Processing :: Linguistic
Classifier: Topic :: Software Development :: Libraries :: Python Modules
